[{"name":"shop","flags":{"edit":true,"god":false,"touch":true},"pos1":[86,68,203],"pos2":[125,75,234],"level":"shop","whitelist":["ghast_noob"]},{"name":"pvp","flags":{"edit":true,"god":false,"touch":true},"pos1":[139,60,208],"pos2":[191,81,157],"level":"pvp","whitelist":["_skull_"]},{"name":"hub","flags":{"edit":true,"god":false,"touch":true},"pos1":[127,64,127],"pos2":[6,111,13],"level":"spawnhub_doomgary_v3","whitelist":["_skull_"]},{"name":"sur","flags":{"edit":true,"god":false,"touch":true},"pos1":[937,146,1050],"pos2":[891,61,1009],"level":"survival","whitelist":["ghast_noob"]}]